blue_sandbox/README.py
blue_sandbox/__init__.py
blue_sandbox/__main__.py
blue_sandbox/config.env
blue_sandbox/env.py
blue_sandbox/functions.py
blue_sandbox/host.py
blue_sandbox/logger.py
blue_sandbox/sample.env
blue_sandbox/urls.py
blue_sandbox/.abcli/abcli.sh
blue_sandbox/.abcli/actions.sh
blue_sandbox/.abcli/aka.sh
blue_sandbox/.abcli/alias.sh
blue_sandbox/.abcli/assets.sh
blue_sandbox/.abcli/blue_sandbox.sh
blue_sandbox/.abcli/browse.sh
blue_sandbox/.abcli/install.sh
blue_sandbox/.abcli/assets/publish.sh
blue_sandbox/.abcli/tests/README.sh
blue_sandbox/.abcli/tests/help.sh
blue_sandbox/.abcli/tests/version.sh
blue_sandbox/WebDAV/__init__.py
blue_sandbox/WebDAV/interface.py
blue_sandbox/assets/__init__.py
blue_sandbox/assets/__main__.py
blue_sandbox/assets/functions.py
blue_sandbox/help/__init__.py
blue_sandbox/help/__main__.py
blue_sandbox/help/functions.py
blue_sandbox/virtualcam/__init__.py
blue_sandbox/virtualcam/__main__.py
blue_sandbox-5.368.1.dist-info/licenses/LICENSE
blue_sandbox-5.368.1.dist-info/METADATA
blue_sandbox-5.368.1.dist-info/WHEEL
blue_sandbox-5.368.1.dist-info/top_level.txt
blue_sandbox-5.368.1.dist-info/RECORD
