Metadata-Version: 2.4
Name: blue_sandbox
Version: 5.368.1
Summary: 🌀 A sandbox for ideas and experiments.
Home-page: https://github.com/kamangir/blue-sandbox
Author: Arash Abadpour (Kamangir)
Author-email: arash@kamangir.net
License: Public Domain
Classifier: Programming Language :: Python :: 3
Classifier: Programming Language :: Unix Shell
Classifier: License :: Public Domain
Classifier: Operating System :: OS Independent
License-File: LICENSE
Requires-Dist: blueness
Requires-Dist: abcli
Requires-Dist: blue-options
Requires-Dist: blue_objects
Requires-Dist: blue_geo
Requires-Dist: blueflow
Requires-Dist: blue_plugin
Requires-Dist: boto3
Requires-Dist: geojson
Requires-Dist: geopandas
Requires-Dist: matplotlib
Requires-Dist: numpy
Requires-Dist: opencv-python
Requires-Dist: pymysql
Requires-Dist: pyyaml
Requires-Dist: pylint
Requires-Dist: pytest
Requires-Dist: python-dotenv[cli]
Requires-Dist: tqdm
Requires-Dist: webdavclient3
Dynamic: author
Dynamic: author-email
Dynamic: classifier
Dynamic: description
Dynamic: description-content-type
Dynamic: home-page
Dynamic: license
Dynamic: license-file
Dynamic: requires-dist
Dynamic: summary
